murano/__init__.py
murano/context.py
murano/opts.py
murano/utils.py
murano/version.py
murano/api/__init__.py
murano/api/versions.py
murano/api/middleware/__init__.py
murano/api/middleware/context.py
murano/api/middleware/fault.py
murano/api/middleware/version_negotiation.py
murano/api/v1/__init__.py
murano/api/v1/actions.py
murano/api/v1/catalog.py
murano/api/v1/deployments.py
murano/api/v1/environments.py
murano/api/v1/instance_statistics.py
murano/api/v1/request_statistics.py
murano/api/v1/router.py
murano/api/v1/schemas.py
murano/api/v1/services.py
murano/api/v1/sessions.py
murano/api/v1/template_applications.py
murano/api/v1/templates.py
murano/cmd/__init__.py
murano/cmd/api.py
murano/cmd/db_manage.py
murano/cmd/engine.py
murano/cmd/manage.py
murano/common/__init__.py
murano/common/auth_utils.py
murano/common/config.py
murano/common/consts.py
murano/common/engine.py
murano/common/exceptions.py
murano/common/i18n.py
murano/common/plugin_loader.py
murano/common/policy.py
murano/common/rpc.py
murano/common/server.py
murano/common/statservice.py
murano/common/utils.py
murano/common/uuidutils.py
murano/common/wsgi.py
murano/common/xmlutils.py
murano/common/helpers/__init__.py
murano/common/helpers/token_sanitizer.py
murano/common/messaging/__init__.py
murano/common/messaging/message.py
murano/common/messaging/mqclient.py
murano/common/messaging/subscription.py
murano/db/__init__.py
murano/db/api.py
murano/db/models.py
murano/db/session.py
murano/db/catalog/__init__.py
murano/db/catalog/api.py
murano/db/migration/__init__.py
murano/db/migration/alembic.ini
murano/db/migration/helpers.py
murano/db/migration/migration.py
murano/db/migration/alembic_migrations/README
murano/db/migration/alembic_migrations/env.py
murano/db/migration/alembic_migrations/script.py.mako
murano/db/migration/alembic_migrations/versions/001_inital_version.py
murano-2015.1.1.dist-info/DESCRIPTION.rst
murano-2015.1.1.dist-info/METADATA
murano-2015.1.1.dist-info/RECORD
murano-2015.1.1.dist-info/WHEEL
murano-2015.1.1.dist-info/entry_points.txt
murano-2015.1.1.dist-info/metadata.json
murano-2015.1.1.dist-info/pbr.json
murano-2015.1.1.dist-info/top_level.txt
