Metadata-Version: 2.0
Name: murano
Version: 2015.1.1
Summary: Murano API
Home-page: https://launchpad.net/murano
Author: OpenStack
Author-email: openstack-dev@lists.openstack.org
License: Apache License, Version 2.0
Platform: UNKNOWN
Classifier: Development Status :: 5 - Production/Stable
Classifier: Environment :: OpenStack
Classifier: Intended Audience :: Developers
Classifier: Intended Audience :: Information Technology
Classifier: License :: OSI Approved :: Apache Software License
Classifier: Operating System :: OS Independent
Classifier: Programming Language :: Python
Requires-Dist: Babel (>=1.3)
Requires-Dist: Paste
Requires-Dist: PasteDeploy (>=1.5.0)
Requires-Dist: PyYAML (>=3.1.0)
Requires-Dist: Routes (>=1.12.3,!=2.0)
Requires-Dist: SQLAlchemy (<=0.9.99,>=0.9.7)
Requires-Dist: WebOb (>=1.2.3)
Requires-Dist: alembic (<0.8.1,>=0.7.2)
Requires-Dist: eventlet (>=0.16.1,!=0.17.0)
Requires-Dist: iso8601 (>=0.1.9)
Requires-Dist: jsonpatch (>=1.1)
Requires-Dist: jsonschema (<3.0.0,>=2.0.0)
Requires-Dist: keystonemiddleware (>=1.5.0,<1.6.0)
Requires-Dist: kombu (>=2.5.0)
Requires-Dist: netaddr (>=0.7.12)
Requires-Dist: oslo.config (<1.10.0,>=1.9.3)
Requires-Dist: oslo.db (<1.8.0,>=1.7.0)
Requires-Dist: oslo.i18n (>=1.5.0,<1.6.0)
Requires-Dist: oslo.messaging (>=1.8.0,<1.9.0)
Requires-Dist: oslo.serialization (<1.5.0,>=1.4.0)
Requires-Dist: oslo.utils (!=1.4.1,<1.5.0,>=1.4.0)
Requires-Dist: pbr (<1.0,!=0.7,>=0.6)
Requires-Dist: psutil (<2.0.0,>=1.1.1)
Requires-Dist: python-congressclient (>=1.0.2)
Requires-Dist: python-heatclient (<0.5.0,>=0.3.0)
Requires-Dist: python-keystoneclient (>=1.2.0,<1.4.0)
Requires-Dist: python-mistralclient (<0.3,>=0.2)
Requires-Dist: python-muranoclient (<0.6.0,>=0.5.6)
Requires-Dist: python-neutronclient (<2.5.0,>=2.4.0)
Requires-Dist: retrying (!=1.3.0,>=1.2.3)
Requires-Dist: six (>=1.9.0)
Requires-Dist: stevedore (<1.4.0,>=1.3.0)
Requires-Dist: yaql (>=0.2.6,<0.3)
